pbi/__init__.py
pbi/deploy.py
pbi/token.py
pbi/tools.py
pbi/api/__init__.py
pbi/api/capacity.py
pbi/api/dataset.py
pbi/api/datasource.py
pbi/api/report.py
pbi/api/tenant.py
pbi/api/workspace.py
pbi_tools-2.3.1.dist-info/LICENSE
pbi_tools-2.3.1.dist-info/METADATA
pbi_tools-2.3.1.dist-info/WHEEL
pbi_tools-2.3.1.dist-info/top_level.txt
pbi_tools-2.3.1.dist-info/RECORD
