Metadata-Version: 2.1
Name: pbi-tools
Version: 2.3.1
Summary: Power BI REST API wrapper and other tools
Home-page: https://github.com/thomas-daughters/pbi-tools
Author: Sam Thomas
Author-email: sam.thomas@redkite.com
License: MIT
Platform: UNKNOWN
License-File: LICENSE
